shorse/__init__.py
shorse/shorse.py
shorse/assets/shorse.png
shorse-0.0.3.dist-info/METADATA
shorse-0.0.3.dist-info/WHEEL
shorse-0.0.3.dist-info/top_level.txt
shorse-0.0.3.dist-info/RECORD
